Workbook

Sheet Test Cases
A1: Module | B1: ID | C1: Test | D1: How to test | E1: Expected result | F1: Verify with | G1: Result | H1: Tester | I1: Date | J1: Notes / defect ref
A2: 1. Environment, Build and Deployment | B2: ENV-01 | C2: Deployed build matches the intended commit | D2: On the VPS run: cd /opt/deskportal && git log --oneline -1. Compare with the commit you expect. Then check the running image is newer than that commit: docker inspect -f '{{.Created}}' $(docker inspect -f '{{.Image}}' desk-portal-prod-api-1) | E2: Repo HEAD equals the intended commit AND the image was built after it. | F2: SSH + docker inspect. If the image predates the commit, the deploy did not rebuild - re-run compose up -d --build before testing anything else. | G2: Not run
A3: 1. Environment, Build and Deployment | B3: ENV-02 | C3: All containers healthy | D3: docker ps --format '{{.Names}}\t{{.Status}}' | grep desk-portal | E3: api, worker, web, postgres, keycloak all Up. Postgres reports (healthy). | F3: Any container restarting in a loop usually means a pending EF migration - check docker logs desk-portal-prod-api-1 for PendingModelChangesWarning. | G3: Not run
A4: 1. Environment, Build and Deployment | B4: ENV-03 | C4: Database migrations are applied and current | D4: Restart the API and watch its log for migration output: docker logs desk-portal-prod-api-1 --since 5m | grep -i migrat | E4: Migrations apply cleanly, or report nothing pending. No PendingModelChangesWarning. | F4: API log. Local mode uses SQLite EnsureCreated and hides schema drift, so this must be checked against Postgres, never only locally. | G4: Not run
A5: 1. Environment, Build and Deployment | B5: ENV-04 | C5: Stale browser tab is detected | D5: Open the dashboard, leave the tab open, deploy a new build, then focus the tab and wait up to 3 minutes. | E5: A Reload toast appears (UpdateWatchdog polls /version against BUILD_ID). | F5: Browser UI. If a tester reports a bug that 'came back', check for a stale bundle first - the tell is old UI details still on screen. | G5: Not run
A6: 1. Environment, Build and Deployment | B6: ENV-05 | C6: TLS and vhost serve the right site | D6: curl -sI https://piomanage.com | head -3 | E6: HTTP 200, valid certificate, no redirect to another site co-hosted on the same VPS. | F6: curl. This VPS also serves pioassets.com and piodeploy.com. | G6: Not run
A7: 2. Authentication and Session | B7: AUTH-01 | C7: Staff login round trip | D7: Open https://piomanage.com, click Sign in, authenticate as a staff user in the desk realm. | E7: Redirected back to /dashboard, header shows the user menu with the right name. | F7: Browser. Check DevTools > Application > Cookies: the session cookie is httpOnly and Secure, and there is NO token in localStorage. | G7: Not run
A8: 2. Authentication and Session | B8: AUTH-02 | C8: First login forces a password change | D8: Create a Keycloak user with a temporary password, then log in as them. | E8: Keycloak forces a password update before the app loads. | F8: Keycloak admin console + browser. | G8: Not run
A9: 2. Authentication and Session | B9: AUTH-03 | C9: Unauthenticated access is blocked | D9: In a private window open https://piomanage.com/dashboard/tickets directly. | E9: Redirected to login, not shown any ticket data. | F9: Browser. Repeat for /control-panel and /dashboard/users. | G9: Not run
A10: 2. Authentication and Session | B10: AUTH-04 | C10: Expired access token refreshes silently | D10: Stay logged in past the access-token lifetime, then click through to another page. | E10: The BFF proxy refreshes on 401 and the page loads without bouncing to login. | F10: Browser network tab: a 401 followed by a successful retry. | G10: Not run
A11: 2. Authentication and Session | B11: AUTH-05 | C11: Logout clears the session | D11: Click Sign out, then press Back and try to reach /dashboard. | E11: Session cookies cleared; the protected page redirects to login. | F11: Browser. | G11: Not run
A12: 2. Authentication and Session | B12: AUTH-06 | C12: A user with no portal record cannot act | D12: Log in as a Keycloak user with no matching app_users / client_users row. | E12: No tenant scope is resolved: the user sees no data rather than another tenant's data. | F12: Browser + SQL: select * from app_users where "IdpSubject"='<keycloak sub>'. | G12: Not run
A13: 2. Authentication and Session | B13: AUTH-07 | C13: Client login is separate from staff login | D13: Log in as a pure client-portal user (client_users row, no app_users row). | E13: Lands in the client experience with exactly tickets.create and tickets.note.public.add; no staff tooling appears on the ticket page. | F13: Browser. A user holding BOTH identities must resolve as staff - test that case too. | G13: Not run
... A239: 23. Regression Traps - Defects Already Found in This Build | B239: REG-10 | C239: Fakes must not be more permissive than the real API | D239: When adding connector behaviour, make the in-memory fake enforce what the provider enforces. | E239: The unit suite fails before production does. Every connector bug in this list was hidden at least once by a fake that accepted something the real API rejects. | F239: dotnet test tests/unit. | G239: Not run

Sheet Summary
A1: Progress by module
A2: Every figure here is a formula over the Test Cases sheet, so it updates itself as testers fill in the Result column. Nothing on this sheet should be typed into.
A4: Module | B4: Cases | C4: Pass | D4: Fail | E4: Blocked | F4: Not run | G4: % done
A5: 1. Environment, Build and Deployment | B5: =COUNTIF('Test Cases'!$A$2:$A$239,$A5) | C5: =COUNTIFS('Test Cases'!$A$2:$A$239,$A5,'Test Cases'!$G$2:$G$239,"Pass") | D5: =COUNTIFS('Test Cases'!$A$2:$A$239,$A5,'Test Cases'!$G$2:$G$239,"Fail") | E5: =COUNTIFS('Test Cases'!$A$2:$A$239,$A5,'Test Cases'!$G$2:$G$239,"Blocked") | F5: =COUNTIFS('Test Cases'!$A$2:$A$239,$A5,'Test Cases'!$G$2:$G$239,"Not run") | G5: =IFERROR(($C5+$D5+$E5)/$B5,0)
A6: 2. Authentication and Session | B6: =COUNTIF('Test Cases'!$A$2:$A$239,$A6) | C6: =COUNTIFS('Test Cases'!$A$2:$A$239,$A6,'Test Cases'!$G$2:$G$239,"Pass") | D6: =COUNTIFS('Test Cases'!$A$2:$A$239,$A6,'Test Cases'!$G$2:$G$239,"Fail") | E6: =COUNTIFS('Test Cases'!$A$2:$A$239,$A6,'Test Cases'!$G$2:$G$239,"Blocked") | F6: =COUNTIFS('Test Cases'!$A$2:$A$239,$A6,'Test Cases'!$G$2:$G$239,"Not run") | G6: =IFERROR(($C6+$D6+$E6)/$B6,0)
A7: 3. Tenant Isolation and Security | B7: =COUNTIF('Test Cases'!$A$2:$A$239,$A7) | C7: =COUNTIFS('Test Cases'!$A$2:$A$239,$A7,'Test Cases'!$G$2:$G$239,"Pass") | D7: =COUNTIFS('Test Cases'!$A$2:$A$239,$A7,'Test Cases'!$G$2:$G$239,"Fail") | E7: =COUNTIFS('Test Cases'!$A$2:$A$239,$A7,'Test Cases'!$G$2:$G$239,"Blocked") | F7: =COUNTIFS('Test Cases'!$A$2:$A$239,$A7,'Test Cases'!$G$2:$G$239,"Not run") | G7: =IFERROR(($C7+$D7+$E7)/$B7,0)
A8: 4. Roles and Permissions | B8: =COUNTIF('Test Cases'!$A$2:$A$239,$A8) | C8: =COUNTIFS('Test Cases'!$A$2:$A$239,$A8,'Test Cases'!$G$2:$G$239,"Pass") | D8: =COUNTIFS('Test Cases'!$A$2:$A$239,$A8,'Test Cases'!$G$2:$G$239,"Fail") | E8: =COUNTIFS('Test Cases'!$A$2:$A$239,$A8,'Test Cases'!$G$2:$G$239,"Blocked") | F8: =COUNTIFS('Test Cases'!$A$2:$A$239,$A8,'Test Cases'!$G$2:$G$239,"Not run") | G8: =IFERROR(($C8+$D8+$E8)/$B8,0)
A9: 5. Staff Users and Technician Registration | B9: =COUNTIF('Test Cases'!$A$2:$A$239,$A9) | C9: =COUNTIFS('Test Cases'!$A$2:$A$239,$A9,'Test Cases'!$G$2:$G$239,"Pass") | D9: =COUNTIFS('Test Cases'!$A$2:$A$239,$A9,'Test Cases'!$G$2:$G$239,"Fail") | E9: =COUNTIFS('Test Cases'!$A$2:$A$239,$A9,'Test Cases'!$G$2:$G$239,"Blocked") | F9: =COUNTIFS('Test Cases'!$A$2:$A$239,$A9,'Test Cases'!$G$2:$G$239,"Not run") | G9: =IFERROR(($C9+$D9+$E9)/$B9,0)
A10: 6. Departments and Teams | B10: =COUNTIF('Test Cases'!$A$2:$A$239,$A10) | C10: =COUNTIFS('Test Cases'!$A$2:$A$239,$A10,'Test Cases'!$G$2:$G$239,"Pass") | D10: =COUNTIFS('Test Cases'!$A$2:$A$239,$A10,'Test Cases'!$G$2:$G$239,"Fail") | E10: =COUNTIFS('Test Cases'!$A$2:$A$239,$A10,'Test Cases'!$G$2:$G$239,"Blocked") | F10: =COUNTIFS('Test Cases'!$A$2:$A$239,$A10,'Test Cases'!$G$2:$G$239,"Not run") | G10: =IFERROR(($C10+$D10+$E10)/$B10,0)
A11: 7. Client Users and the Client Portal | B11: =COUNTIF('Test Cases'!$A$2:$A$239,$A11) | C11: =COUNTIFS('Test Cases'!$A$2:$A$239,$A11,'Test Cases'!$G$2:$G$239,"Pass") | D11: =COUNTIFS('Test Cases'!$A$2:$A$239,$A11,'Test Cases'!$G$2:$G$239,"Fail") | E11: =COUNTIFS('Test Cases'!$A$2:$A$239,$A11,'Test Cases'!$G$2:$G$239,"Blocked") | F11: =COUNTIFS('Test Cases'!$A$2:$A$239,$A11,'Test Cases'!$G$2:$G$239,"Not run") | G11: =IFERROR(($C11+$D11+$E11)/$B11,0)
A12: 8. PSA Connections | B12: =COUNTIF('Test Cases'!$A$2:$A$239,$A12) | C12: =COUNTIFS('Test Cases'!$A$2:$A$239,$A12,'Test Cases'!$G$2:$G$239,"Pass") | D12: =COUNTIFS('Test Cases'!$A$2:$A$239,$A12,'Test Cases'!$G$2:$G$239,"Fail") | E12: =COUNTIFS('Test Cases'!$A$2:$A$239,$A12,'Test Cases'!$G$2:$G$239,"Blocked") | F12: =COUNTIFS('Test Cases'!$A$2:$A$239,$A12,'Test Cases'!$G$2:$G$239,"Not run") | G12: =IFERROR(($C12+$D12+$E12)/$B12,0)
A13: 9. Field Mapping | B13: =COUNTIF('Test Cases'!$A$2:$A$239,$A13) | C13: =COUNTIFS('Test Cases'!$A$2:$A$239,$A13,'Test Cases'!$G$2:$G$239,"Pass") | D13: =COUNTIFS('Test Cases'!$A$2:$A$239,$A13,'Test Cases'!$G$2:$G$239,"Fail") | E13: =COUNTIFS('Test Cases'!$A$2:$A$239,$A13,'Test Cases'!$G$2:$G$239,"Blocked") | F13: =COUNTIFS('Test Cases'!$A$2:$A$239,$A13,'Test Cases'!$G$2:$G$239,"Not run") | G13: =IFERROR(($C13+$D13+$E13)/$B13,0)
A14: 10. Ticket Sync Engine | B14: =COUNTIF('Test Cases'!$A$2:$A$239,$A14) | C14: =COUNTIFS('Test Cases'!$A$2:$A$239,$A14,'Test Cases'!$G$2:$G$239,"Pass") | D14: =COUNTIFS('Test Cases'!$A$2:$A$239,$A14,'Test Cases'!$G$2:$G$239,"Fail") | E14: =COUNTIFS('Test Cases'!$A$2:$A$239,$A14,'Test Cases'!$G$2:$G$239,"Blocked") | F14: =COUNTIFS('Test Cases'!$A$2:$A$239,$A14,'Test Cases'!$G$2:$G$239,"Not run") | G14: =IFERROR(($C14+$D14+$E14)/$B14,0)
A15: 11. Ticket Lifecycle in the Portal | B15: =COUNTIF('Test Cases'!$A$2:$A$239,$A15) | C15: =COUNTIFS('Test Cases'!$A$2:$A$239,$A15,'Test Cases'!$G$2:$G$239,"Pass") | D15: =COUNTIFS('Test Cases'!$A$2:$A$239,$A15,'Test Cases'!$G$2:$G$239,"Fail") | E15: =COUNTIFS('Test Cases'!$A$2:$A$239,$A15,'Test Cases'!$G$2:$G$239,"Blocked") | F15: =COUNTIFS('Test Cases'!$A$2:$A$239,$A15,'Test Cases'!$G$2:$G$239,"Not run") | G15: =IFERROR(($C15+$D15+$E15)/$B15,0)
A16: 12. Notes, Conversation and Recipients | B16: =COUNTIF('Test Cases'!$A$2:$A$239,$A16) | C16: =COUNTIFS('Test Cases'!$A$2:$A$239,$A16,'Test Cases'!$G$2:$G$239,"Pass") | D16: =COUNTIFS('Test Cases'!$A$2:$A$239,$A16,'Test Cases'!$G$2:$G$239,"Fail") | E16: =COUNTIFS('Test Cases'!$A$2:$A$239,$A16,'Test Cases'!$G$2:$G$239,"Blocked") | F16: =COUNTIFS('Test Cases'!$A$2:$A$239,$A16,'Test Cases'!$G$2:$G$239,"Not run") | G16: =IFERROR(($C16+$D16+$E16)/$B16,0)
... A27: 23. Regression Traps - Defects Already Found in This Build | B27: =COUNTIF('Test Cases'!$A$2:$A$239,$A27) | C27: =COUNTIFS('Test Cases'!$A$2:$A$239,$A27,'Test Cases'!$G$2:$G$239,"Pass") | D27: =COUNTIFS('Test Cases'!$A$2:$A$239,$A27,'Test Cases'!$G$2:$G$239,"Fail") | E27: =COUNTIFS('Test Cases'!$A$2:$A$239,$A27,'Test Cases'!$G$2:$G$239,"Blocked") | F27: =COUNTIFS('Test Cases'!$A$2:$A$239,$A27,'Test Cases'!$G$2:$G$239,"Not run") | G27: =IFERROR(($C27+$D27+$E27)/$B27,0)
A28: Total | B28: =SUM(B5:B27) | C28: =SUM(C5:C27) | D28: =SUM(D5:D27) | E28: =SUM(E5:E27) | F28: =SUM(F5:F27) | G28: =IFERROR(($C28+$D28+$E28)/$B28,0)

Sheet How to use
A1: Desk Portal / PIO Manage - test case workbook
A3: Fill in | B3: On the Test Cases sheet, only the four SHADED columns are yours: Result, Tester, Date and Notes / defect ref. Everything to their left is the plan and should not be edited here - change it in the generator so the PDF and this workbook stay in step.
A4: Result | B4: Pick from the dropdown: Not run, Pass, Fail, Blocked, N/A. The cell colours itself, and the Summary sheet recounts automatically.
A5: Filtering | B5: Row 1 has filters. Filter Module to work one area at a time, or Result = Fail to review defects.
A7: Three rules | B7: These decide whether a pass means anything in this system:
B8: 1. Confirm the build under test is newer than the fix you are testing. More time has been lost here to stale builds than to real defects.
B9: 2. A check that matches something already true is not a check. When waiting on a sync or a rollup, capture the current timestamp first and wait for a DIFFERENT one.
B10: 3. Absence of an error is not evidence. An unmapped value, a skipped ticket and a truncated import all look exactly like normal successful operation.
A12: Example row | B12: How a completed row should look:
A13: ID | B13: Result | C13: Tester | D13: Date | E13: Notes / defect ref
A14: SYNC-02 | B14: Fail | C14: A. Tester | D14: 2026-09-08 | E14: Imported 100 of 135. Raised DESK-412.
A16: Not covered | B16: Stated so nobody assumes otherwise: there is no SMTP anywhere in the stack, so email delivery cannot be tested - enquiries and reports are stored for in-portal download. Load testing, DAST and penetration testing are authored but have never run against the live stack. Disaster recovery is documented but never rehearsed. ConnectWise closure dates cannot be verified until a ticket is actually closed in that sandbox, and the legal pages still contain unfilled placeholders.

Sheet Reference
A1: Reference - access, SQL and log lines
A3: Getting in
A4: Database | B4: docker exec desk-portal-prod-postgres-1 psql -U desk -d desk_portal -c "<query>"
A5: Worker log | B5: docker logs desk-portal-prod-worker-1 --since 30m
A6: Unit suite | B6: dotnet test tests/unit
A8: SQL cookbook
A9: Is anything actually mapping? | B9: select c."Name", count(*) tickets, count(*) filter (where t."PsaStatus"=t."PortalStatus") status_raw, count(*) filter (where t."PsaPriority"=t."PortalPriority") priority_raw from tickets t join psa_connections c on c."Id"=t."PsaConnectionId" group by 1;
A10: Date coverage | B10: select c."Name", count(*) total, count(t."PsaCreatedAt") raised, count(t."SlaDueAt") sla, count(t."ClosedAt") closed from tickets t join psa_connections c on c."Id"=t."PsaConnectionId" group by 1;
A11: Inbound mapping ambiguity (must return 0 rows) | B11: select "PsaConnectionId","PortalField","ExternalValue",count(*) from field_mappings where "IsActive" and "Direction" in (2,3) group by 1,2,3 having count(*)>1;
A12: Outbound mapping ambiguity (must return 0 rows) | B12: select "PsaConnectionId","PortalField","PortalValue",count(*) from field_mappings where "IsActive" and "Direction" in (1,3) group by 1,2,3 having count(*)>1;
A13: Duplicate tickets after a paginated import (must return 0 rows) | B13: select "PsaConnectionId","ExternalTicketId",count(*) from tickets group by 1,2 having count(*)>1;
A14: Connection health | B14: select "Name","Status","IsEnabled","LastSuccessfulSyncAt","LastError" from psa_connections;
A15: Force a full re-sync of everything | B15: update psa_connections set "LastSuccessfulSyncAt"=NULL;
A16: Activity rollup state | B16: select (select count(*) from activity_events) events, (select count(*) from activity_daily_facts) facts, (select sum("EventCount") from activity_daily_facts) rolled_up;
A17: Events by the day they happened | B17: select "OccurredAt"::date d, count(*) from activity_events group by 1 order by 1;
A18: Open-ticket count as the client report computes it | B18: select count(*) from tickets where "PortalStatus" in ('NEW','IN_PROGRESS','WAITING_CUSTOMER','ON_HOLD');
A19: All mapping rules for one connection | B19: select "PortalField","PortalValue","ExternalValue","Direction","IsActive" from field_mappings where "PsaConnectionId"='<id>' order by 1,2;
A21: Log lines worth grepping
A22: No mapping rule matches | B22: A provider value nothing maps. Once per sync run.
A23: Scheduled sync failed | B23: A connection's sync threw. The exception follows in @x.
A24: safety cap | B24: The run stopped at 50 pages with more to read - the import is incomplete.
A25: Activity rollup: | B25: Days recomputed, facts written, raw events expired.
A26: picklist | B26: Autotask option ids and labels - use it to read a rule that holds a bare id.
A27: ConnectWise ticket fields | B27: Which fields the provider actually sent, unioned across the page. Field names only.
